pyinvestingsnippets/__init__.py
pyinvestingsnippets/exceptions/__init__.py
pyinvestingsnippets/exceptions/cwi_not_properly_called_exception.py
pyinvestingsnippets/extensions/__init__.py
pyinvestingsnippets/extensions/annual_returns.py
pyinvestingsnippets/extensions/cumulative_wealth_index.py
pyinvestingsnippets/extensions/cwi.py
pyinvestingsnippets/extensions/drawdown.py
pyinvestingsnippets/extensions/drawdown_durations.py
pyinvestingsnippets/extensions/log_returns.py
pyinvestingsnippets/extensions/monthly_returns.py
pyinvestingsnippets/extensions/prices.py
pyinvestingsnippets/extensions/returns.py
pyinvestingsnippets/extensions/srri.py
pyinvestingsnippets/extensions/wealthindex.py
pyinvestingsnippets/extensions/weekly_returns.py
pyinvestingsnippets/utilities/__init__.py
pyinvestingsnippets/utilities/beta_covariance.py
pyinvestingsnippets/utilities/beta_regression.py
pyinvestingsnippets/utilities/exponentially_weighted_downside_risk.py
pyinvestingsnippets/utilities/rolling_beta_covariance.py
pyinvestingsnippets/utilities/rolling_beta_regression.py
pyinvestingsnippets/utilities/rolling_realized_volatility.py
pyinvestingsnippets/utilities/rolling_returns.py
pyinvestingsnippets/utilities/rolling_volatility.py
tests/extensions/__init__.py
tests/extensions/test_cwi.py
tests/extensions/test_drawdown.py
tests/extensions/test_drawdown_durations.py
tests/extensions/test_log_returns.py
tests/extensions/test_prices.py
tests/extensions/test_returns.py
tests/extensions/test_srri.py
tests/extensions/test_wealthindex.py
tests/utilities/__init__.py
tests/utilities/test_rolling_returns.py
tests/utilities/test_rolling_volatility.py
pyinvestingsnippets-4.0.1.dist-info/LICENSE.txt
pyinvestingsnippets-4.0.1.dist-info/METADATA
pyinvestingsnippets-4.0.1.dist-info/WHEEL
pyinvestingsnippets-4.0.1.dist-info/top_level.txt
pyinvestingsnippets-4.0.1.dist-info/RECORD
