Metadata-Version: 2.1
Name: pyinvestingsnippets
Version: 4.0.1
Home-page: https://pyinvestingsnippets.readthedocs.io/
Author: InvestingSnippets
Author-email: investingsnippets@gmail.com
License: MIT License
Project-URL: Bug Reports, https://github.com/investingsnippets/pyinvestingsnippets/issues
Project-URL: Source, https://github.com/investingsnippets/pyinvestingsnippets
Project-URL: Documentation, https://pyinvestingsnippets.readthedocs.io/
Keywords: investing,financial-data,pandas
Classifier: Programming Language :: Python :: 3 :: Only
Classifier: Programming Language :: Python :: 3.7
Classifier: Programming Language :: Python :: 3.8
Classifier: Programming Language :: Python :: 3.9
Classifier: License :: OSI Approved :: MIT License
Classifier: Intended Audience :: Developers
Classifier: Topic :: Office/Business :: Financial
Classifier: Topic :: Office/Business :: Financial :: Investment
Classifier: Topic :: Scientific/Engineering :: Information Analysis
Classifier: Topic :: Software Development :: Libraries
Requires-Python: >=3.7
License-File: LICENSE.txt
Requires-Dist: scikit-learn (>=1.0.2)
Requires-Dist: seaborn (>=0.11.2)
Requires-Dist: matplotlib (>=3.5.1)
Requires-Dist: scipy (>=1.7.3)
Requires-Dist: pandas (>=1.3.5)
Requires-Dist: numpy (>=1.21.5)
Requires-Dist: plotly (>=5.6.0)
Provides-Extra: tests
Requires-Dist: pytest (<=6.2.5,>=2.8.0) ; extra == 'tests'
Requires-Dist: pytest-cov ; extra == 'tests'
Requires-Dist: pytest-mock (==2.0.0) ; extra == 'tests'
